dhydro2isg/__init__.py
dhydro2isg/config.py
dhydro2isg/dhydro2isg.py
dhydro2isg/dhydro_geometry.py
dhydro2isg/helper.py
dhydro2isg/isc_files.py
dhydro2isg/isg.py
dhydro2isg/readwrite.py
dhydro2isg/stf.py
dhydro2isg/stf_funcs.py
dhydro2isg-1.0.0.dist-info/licenses/LICENSE
dhydro2isg-1.0.0.dist-info/METADATA
dhydro2isg-1.0.0.dist-info/WHEEL
dhydro2isg-1.0.0.dist-info/top_level.txt
dhydro2isg-1.0.0.dist-info/RECORD
