Metadata-Version: 2.4
Name: dhydro2isg
Version: 1.0.0
Summary: Convert D-HYDRO output to ISG
Author: Haskoning
License: GPL-3.0-or-later
Project-URL: Homepage, https://github.com/RoyalHaskoningDHV/dhydro2isg
Project-URL: Bug Reports, https://github.com/RoyalHaskoningDHV/dhydro2isg/issues
Project-URL: Source, https://github.com/RoyalHaskoningDHVdhydro2isg
Keywords: dhydro,imod,hydrology,modeling
Classifier: Development Status :: 3 - Alpha
Classifier: Intended Audience :: Science/Research
Classifier: Operating System :: OS Independent
Classifier: Programming Language :: Python :: 3
Classifier: Programming Language :: Python :: 3.8
Classifier: Programming Language :: Python :: 3.9
Classifier: Programming Language :: Python :: 3.10
Classifier: Programming Language :: Python :: 3.11
Classifier: Programming Language :: Python :: 3.12
Classifier: Programming Language :: Python :: 3.13
Classifier: Topic :: Scientific/Engineering
Requires-Python: <3.14,>=3.12
License-File: LICENSE
Requires-Dist: netCDF4
Requires-Dist: tqdm
Requires-Dist: matplotlib
Requires-Dist: numpy
Requires-Dist: scipy
Requires-Dist: pandas<3.0,>=2.3.3
Requires-Dist: shapely>=2.0
Requires-Dist: sympy
Requires-Dist: geopandas<2.0,>=1.1.1
Requires-Dist: xarray
Requires-Dist: jupyter
Requires-Dist: plotly
Requires-Dist: pydantic>1.10
Requires-Dist: kaleido
Requires-Dist: fiona
Provides-Extra: dev
Requires-Dist: pytest>=6.0; extra == "dev"
Requires-Dist: pytest-cov>=2.0; extra == "dev"
Requires-Dist: flake8>=3.8; extra == "dev"
Requires-Dist: black>=21.0; extra == "dev"
Requires-Dist: twine>=3.0; extra == "dev"
Requires-Dist: build>=0.7; extra == "dev"
Dynamic: license-file
